staffspy/__init__.py
staffspy/capsolver.py
staffspy/exceptions.py
staffspy/linkedin/certifications.py
staffspy/linkedin/employee.py
staffspy/linkedin/employee_bio.py
staffspy/linkedin/experiences.py
staffspy/linkedin/linkedin.py
staffspy/linkedin/schools.py
staffspy/linkedin/skills.py
staffspy/models.py
staffspy/utils.py
staffspy_enhanced-0.2.5.dist-info/LICENSE
staffspy_enhanced-0.2.5.dist-info/METADATA
staffspy_enhanced-0.2.5.dist-info/WHEEL
staffspy_enhanced-0.2.5.dist-info/RECORD
